<Module>
  <Name value="Detailed Character Creation" />
  <Id value="zzCharacterCreation" />
  <Version value="v1.1.13" />
  <SingleplayerModule value="true" />
  <MultiplayerModule value="false" />
  <DependedModules>
    <DependedModule Id="Native"/>
    <DependedModule Id="SandBoxCore"/>
    <DependedModule Id="Sandbox"/>
    <DependedModule Id="CustomBattle"/>
    <DependedModule Id="StoryMode"/>
  </DependedModules>
  <SubModules>
    <SubModule>
      <Name value="CharacterCreation" />
      <DLLName value="CharacterCreation.dll" />
      <SubModuleClassType value="CharacterCreation.SubModule" />
      <Tags>
        <Tag key="DedicatedServerType" value="none" />
        <Tag key="IsNoRenderModeElement" value="false" />
      </Tags>
    </SubModule>
    <SubModule>
      <Name value="MCMv3 Integrated Loader" />
      <DLLName value="MCMv3.dll" />
      <SubModuleClassType value="MCM.IntegratedLoaderSubModule" />
      <Tags>
        <Tag key="DedicatedServerType" value="none" />
        <Tag key="IsNoRenderModeElement" value="false" />
      </Tags>
    </SubModule>
  </SubModules>
  <Xmls>
    <XmlNode>
      <XmlName id="strings" path="strings" />
      <IncludedGameTypes>
        <GameType value = "Campaign" />
        <GameType value = "CampaignStoryMode" />
      </IncludedGameTypes>
    </XmlNode>
    <XmlNode>
    <XmlName id="soln_skins" path="skins" />
    <IncludedGameTypes>
      <GameType value = "Campaign" />
      <GameType value = "CampaignStoryMode" />
    </IncludedGameTypes>
    </XmlNode>
  </Xmls>
</Module>